clearshell/__init__.py
clearshell/cli.py
clearshell/decrypt.py
clearshell-1.2.16.dist-info/METADATA
clearshell-1.2.16.dist-info/WHEEL
clearshell-1.2.16.dist-info/entry_points.txt
clearshell-1.2.16.dist-info/top_level.txt
clearshell-1.2.16.dist-info/RECORD
