Metadata-Version: 2.1
Name: clearshell
Version: 1.2.16
Summary: A package to decrypt bash scripts obfuscated with eval.
Home-page: https://github.com/ByteBreach/clearshell
Author: Fidal
Author-email: mrfidal@proton.me
Classifier: Programming Language :: Python :: 3
Classifier: License :: OSI Approved :: MIT License
Classifier: Operating System :: OS Independent
Requires-Python: >=3.6
